codat_bankfeeds/__init__.py
codat_bankfeeds/_hooks/__init__.py
codat_bankfeeds/_hooks/registration.py
codat_bankfeeds/_hooks/sdkhooks.py
codat_bankfeeds/_hooks/types.py
codat_bankfeeds/_version.py
codat_bankfeeds/account_mapping.py
codat_bankfeeds/bank_accounts.py
codat_bankfeeds/basesdk.py
codat_bankfeeds/companies.py
codat_bankfeeds/company_information.py
codat_bankfeeds/configuration.py
codat_bankfeeds/connections.py
codat_bankfeeds/httpclient.py
codat_bankfeeds/models/__init__.py
codat_bankfeeds/models/errors/__init__.py
codat_bankfeeds/models/errors/errormessage.py
codat_bankfeeds/models/errors/sdkerror.py
codat_bankfeeds/models/operations/__init__.py
codat_bankfeeds/models/operations/create_bank_account.py
codat_bankfeeds/models/operations/create_bank_account_mapping.py
codat_bankfeeds/models/operations/create_bank_transactions.py
codat_bankfeeds/models/operations/create_batch_source_account.py
codat_bankfeeds/models/operations/create_connection.py
codat_bankfeeds/models/operations/create_source_account.py
codat_bankfeeds/models/operations/delete_bank_feed_credentials.py
codat_bankfeeds/models/operations/delete_company.py
codat_bankfeeds/models/operations/delete_connection.py
codat_bankfeeds/models/operations/delete_source_account.py
codat_bankfeeds/models/operations/generate_credentials.py
codat_bankfeeds/models/operations/get_bank_account_mapping.py
codat_bankfeeds/models/operations/get_company.py
codat_bankfeeds/models/operations/get_company_access_token.py
codat_bankfeeds/models/operations/get_company_information.py
codat_bankfeeds/models/operations/get_configuration.py
codat_bankfeeds/models/operations/get_connection.py
codat_bankfeeds/models/operations/get_create_bank_transactions_model.py
codat_bankfeeds/models/operations/get_create_bankaccounts_model.py
codat_bankfeeds/models/operations/get_create_operation.py
codat_bankfeeds/models/operations/get_last_successful.py
codat_bankfeeds/models/operations/list_bank_accounts.py
codat_bankfeeds-11.1.0.dist-info/METADATA
codat_bankfeeds-11.1.0.dist-info/WHEEL
codat_bankfeeds-11.1.0.dist-info/RECORD
